lohar/__init__.py
lohar/cli.py
lohar/crypto.py
lohar/init.py
lohar/metadata.py
lohar-0.1.1.dist-info/METADATA
lohar-0.1.1.dist-info/WHEEL
lohar-0.1.1.dist-info/entry_points.txt
lohar-0.1.1.dist-info/RECORD
